scm203lab367112755/__init__.py
scm203lab367112755/lab3mod167112755.py
scm203lab367112755-0.1.0.dist-info/METADATA
scm203lab367112755-0.1.0.dist-info/WHEEL
scm203lab367112755-0.1.0.dist-info/top_level.txt
scm203lab367112755-0.1.0.dist-info/RECORD
