Metadata-Version: 2.4
Name: scm203lab367112755
Version: 0.1.0
Summary: Number theory: Euclidean Algorithm ,Extended Euclidean Algorithm and Sieve of Eratosthenes.
Home-page: https://github.com/yourusername/mypackage
Author: Lewan
Author-email: natthapong.nn@mail.wu.ac.th
Requires-Python: >=3.7
Dynamic: author
Dynamic: author-email
Dynamic: description
Dynamic: description-content-type
Dynamic: home-page
Dynamic: requires-python
Dynamic: summary
